wpexport/__about__.py
wpexport/__init__.py
wpexport/__main__.py
wpexport/cls.py
wpexport-0.0.2.dist-info/METADATA
wpexport-0.0.2.dist-info/RECORD
wpexport-0.0.2.dist-info/WHEEL
wpexport-0.0.2.dist-info/entry_points.txt
wpexport-0.0.2.dist-info/top_level.txt
