Metadata-Version: 2.1
Name: wpexport
Version: 0.0.2
Summary: Backup your Wordpress post to GitHub or local
Home-page: https://github.com/axju/wpexport
Author: Axel Juraske
Author-email: axel.juraske@short-report.de
License: MIT
Keywords: github wordpress backup sync
Platform: UNKNOWN
Requires-Dist: gitpython
Requires-Dist: python-wordpress-xmlrpc
Requires-Dist: pypandoc
